autorok/__init__.py
autorok/autorok.py
autorok/common.py
autorok/devices.py
autorok/libsigrok.py
autorok/sigrokcli.py
autorok-0.1.dist-info/LICENSE.md
autorok-0.1.dist-info/METADATA
autorok-0.1.dist-info/WHEEL
autorok-0.1.dist-info/top_level.txt
autorok-0.1.dist-info/RECORD
