Metadata-Version: 2.1
Name: autorok
Version: 0.1
Summary: Automate sigrok with python-based sigrok-cli wrapper and more!
Author-email: Damian Zaręba <damianzrb@zohomail.eu>
Classifier: Development Status :: 3 - Alpha
Classifier: License :: OSI Approved :: GNU General Public License v3 (GPLv3)
Classifier: Operating System :: OS Independent
Classifier: Programming Language :: Python
Classifier: Topic :: Scientific/Engineering
Requires-Python: >=3.8
License-File: LICENSE.md
Requires-Dist: typeguard (==2.13.3)
Provides-Extra: dev
Requires-Dist: pytest (==7.2.0) ; extra == 'dev'
Requires-Dist: pylint (==2.5.17) ; extra == 'dev'
